Metadata-Version: 1.1
Name: figlib
Version: 1.0.1
Summary: A library for program configuration.
Home-page: http://pypi.python.org/pypi/figlib/
Author: Amol Umrale
Author-email: babaiscool@gmail.com
License: UNKNOWN
Platform: UNKNOWN
Classifier: Development Status :: 4 - Beta
Classifier: License :: OSI Approved :: MIT License
Classifier: Natural Language :: English
Classifier: Operating System :: POSIX :: Linux
Classifier: Operating System :: Microsoft :: Windows
